Metadata-Version: 1.1
Name: humhelpers
Version: 0.1.4
Summary: Different shortcuts functions (helpers) for humanity.
Home-page: https://bitbucket.org/vlad1777d/humhelpers
Author: vlad1777d (Vladislav Naumov)
Author-email: naumovvladislav@mail.ru
License: UNKNOWN
Platform: UNKNOWN
Classifier: Programming Language :: Python :: 3
Classifier: License :: OSI Approved :: MIT License
Classifier: Operating System :: OS Independent
